behave_reportportal/__init__.py
behave_reportportal/behave_agent.py
behave_reportportal/config.py
behave_reportportal/utils.py
behave_reportportal-5.0.1.dist-info/licenses/LICENSE
behave_reportportal-5.0.1.dist-info/METADATA
behave_reportportal-5.0.1.dist-info/WHEEL
behave_reportportal-5.0.1.dist-info/top_level.txt
behave_reportportal-5.0.1.dist-info/RECORD
