Metadata-Version: 2.4
Name: behave-reportportal
Version: 5.0.1
Summary: Agent for reporting Behave results to the ReportPortal
Home-page: https://github.com/reportportal/agent-python-behave
Author: ReportPortal Team
Author-email: support@reportportal.io
License: Apache 2.0
Keywords: testing,reporting,reportportal,behave
Classifier: License :: OSI Approved :: Apache Software License
Classifier: Programming Language :: Python :: 3.8
Classifier: Programming Language :: Python :: 3.9
Classifier: Programming Language :: Python :: 3.10
Classifier: Programming Language :: Python :: 3.11
Classifier: Programming Language :: Python :: 3.12
Classifier: Programming Language :: Python :: 3.13
Requires-Python: >=3.8
License-File: LICENSE
Requires-Dist: behave<2.0,>=1.3.3
Requires-Dist: prettytable
Requires-Dist: reportportal-client~=5.6.6
Dynamic: author
Dynamic: author-email
Dynamic: classifier
Dynamic: description
Dynamic: description-content-type
Dynamic: home-page
Dynamic: keywords
Dynamic: license
Dynamic: license-file
Dynamic: requires-dist
Dynamic: requires-python
Dynamic: summary
